mtcli_rsi/__init__.py
mtcli_rsi/conf.py
mtcli_rsi/plugin.py
mtcli_rsi/rsi.py
mtcli_rsi-1.0.1.dist-info/entry_points.txt
mtcli_rsi-1.0.1.dist-info/LICENSE
mtcli_rsi-1.0.1.dist-info/METADATA
mtcli_rsi-1.0.1.dist-info/WHEEL
mtcli_rsi-1.0.1.dist-info/RECORD
