Metadata-Version: 2.3
Name: mtcli-rsi
Version: 1.0.1
Summary: Plugin mtcli do indicador RSI
License: GPL-3.0
Author: Valmir França da Silva
Author-email: vfranca3@gmail.com
Requires-Python: >=3.10,<3.14.0
Classifier: License :: OSI Approved :: GNU General Public License v3 (GPLv3)
Classifier: Programming Language :: Python :: 3
Classifier: Programming Language :: Python :: 3.10
Classifier: Programming Language :: Python :: 3.11
Classifier: Programming Language :: Python :: 3.12
Classifier: Programming Language :: Python :: 3.13
Requires-Dist: mtcli (>=1.18.1)
Requires-Dist: pandas (>=2.3.2,<3.0.0)
Project-URL: Documentation, https://mtcli-rsi.readthedocs.io
Project-URL: Homepage, https://github.com/vfranca/mtcli-rsi
Project-URL: Repository, https://github.com/vfranca/mtcli-rsi
Project-URL: issues, https://github.com/vfranca/mtcli-rsi/issues
